jaxl/api/__init__.py
jaxl/api/_client.py
jaxl/api/_sdk.py
jaxl/api/base.py
jaxl/api/cli.py
jaxl/api/py.typed
jaxl/api/client/__init__.py
jaxl/api/client/_scm_version.py
jaxl/api/client/client.py
jaxl/api/client/errors.py
jaxl/api/client/types.py
jaxl/api/client/api/__init__.py
jaxl/api/client/api/v1/__init__.py
jaxl/api/client/api/v1/v1_app_organizations_list.py
jaxl/api/client/api/v1/v1_app_organizations_providers_list.py
jaxl/api/client/api/v1/v1_appusers_me_retrieve.py
jaxl/api/client/api/v1/v1_calls_add_create.py
jaxl/api/client/api/v1/v1_calls_audio_retrieve.py
jaxl/api/client/api/v1/v1_calls_hangup_retrieve.py
jaxl/api/client/api/v1/v1_calls_list.py
jaxl/api/client/api/v1/v1_calls_messages_create.py
jaxl/api/client/api/v1/v1_calls_report_retrieve.py
jaxl/api/client/api/v1/v1_calls_retrieve.py
jaxl/api/client/api/v1/v1_calls_tags_create.py
jaxl/api/client/api/v1/v1_calls_token_create.py
jaxl/api/client/api/v1/v1_calls_transfer_create.py
jaxl/api/client/api/v1/v1_calls_tts_create.py
jaxl/api/client/api/v1/v1_calls_usage_retrieve.py
jaxl/api/client/api/v1/v1_campaign_list.py
jaxl/api/client/api/v1/v1_customer_consumables_retrieve.py
jaxl/api/client/api/v1/v1_devices_attest_create.py
jaxl/api/client/api/v1/v1_devices_list.py
jaxl/api/client/api/v1/v1_integrations_create.py
jaxl/api/client/api/v1/v1_ivr_create.py
jaxl/api/client/api/v1/v1_ivr_list.py
jaxl/api/client/api/v1/v1_ivr_options_create.py
jaxl/api/client/api/v1/v1_ivr_options_list.py
jaxl/api/client/api/v1/v1_ivr_options_partial_update.py
jaxl/api/client/api/v1/v1_kyc_list.py
jaxl/api/client/api/v1/v1_messages_list.py
jaxl/api/client/api/v1/v1_phonenumbers_list.py
jaxl/api/client/api/v1/v1_phonenumbers_partial_update.py
jaxl/api/client/api/v1/v1_phonenumbers_search_retrieve.py
jaxl/api/client/api/v2/__init__.py
jaxl/api/client/api/v2/v2_app_organizations_employees_list.py
jaxl/api/client/api/v2/v2_app_organizations_groups_list.py
jaxl/api/client/api/v3/__init__.py
jaxl_python-0.0.28.dist-info/licenses/LICENSE.md
jaxl_python-0.0.28.dist-info/METADATA
jaxl_python-0.0.28.dist-info/WHEEL
jaxl_python-0.0.28.dist-info/entry_points.txt
jaxl_python-0.0.28.dist-info/top_level.txt
jaxl_python-0.0.28.dist-info/RECORD
