Metadata-Version: 2.4
Name: jaxl-python
Version: 0.0.28
Summary: Official Python SDK and CLI for interfacing with the Jaxl API. Manage calls, messages, IVRs, devices, teams, payments, campaigns, streaming transcriptions and AI Agents. Built on OpenAPI, it offers both generated API clients and Pythonic wrappers for ease of use.
Home-page: https://github.com/jaxl-innovations-private-limited/jaxl-python
Download-URL: https://github.com/jaxl-innovations-private-limited/jaxl-python/archive/main.zip
Author: Jaxl Innovations Private Limited
Author-email: engineering@jaxl.com
License: 'Proprietary'
Project-URL: CI: GitHub, https://github.com/jaxl-innovations-private-limited/jaxl-python/actions
Project-URL: GitHub: discussions, https://github.com/jaxl-innovations-private-limited/jaxl-python/discussions
Project-URL: GitHub: issues, https://github.com/jaxl-innovations-private-limited/jaxl-python/issues
Project-URL: GitHub: repo, https://github.com/jaxl-innovations-private-limited/jaxl-python
Keywords: jaxl,api,client,sdk,openapi
Classifier: Development Status :: 5 - Production/Stable
Classifier: Environment :: Console
Classifier: Environment :: No Input/Output (Daemon)
Classifier: Environment :: Web Environment
Classifier: Environment :: MacOS X
Classifier: Environment :: Plugins
Classifier: Environment :: Win32 (MS Windows)
Classifier: Natural Language :: English
Classifier: Operating System :: MacOS
Classifier: Operating System :: MacOS :: MacOS 9
Classifier: Operating System :: MacOS :: MacOS X
Classifier: Operating System :: POSIX
Classifier: Operating System :: POSIX :: Linux
Classifier: Operating System :: Unix
Classifier: Operating System :: Microsoft
Classifier: Operating System :: Microsoft :: Windows
Classifier: Operating System :: Microsoft :: Windows :: Windows 10
Classifier: Operating System :: Android
Classifier: Operating System :: OS Independent
Classifier: Programming Language :: Python :: Implementation
Classifier: Programming Language :: Python :: 3 :: Only
Classifier: Programming Language :: Python :: 3
Classifier: Programming Language :: Python :: 3.6
Classifier: Programming Language :: Python :: 3.7
Classifier: Programming Language :: Python :: 3.8
Classifier: Programming Language :: Python :: 3.9
Classifier: Programming Language :: Python :: 3.10
Classifier: Programming Language :: Python :: 3.11
Classifier: Programming Language :: Python :: 3.12
Classifier: Typing :: Typed
Requires-Python: >=3.9
License-File: LICENSE.md
Requires-Dist: httpx==0.28.1
Requires-Dist: attrs>=21.3.0
Requires-Dist: python-dateutil<3,>=2.8.0
Requires-Dist: cryptography==46.0.2
Requires-Dist: PyJWT==2.8.0
Requires-Dist: requests==2.32.4
Requires-Dist: pydantic==2.11.9
Provides-Extra: dev
Requires-Dist: isort; extra == "dev"
Requires-Dist: mypy; extra == "dev"
Requires-Dist: autoflake; extra == "dev"
Requires-Dist: pylint==3.3.3; extra == "dev"
Provides-Extra: docs
Requires-Dist: pdoc3==0.11.6; extra == "docs"
Requires-Dist: mkdocs==1.6.1; extra == "docs"
Requires-Dist: mkdocstrings==0.30.1; extra == "docs"
Requires-Dist: mkdocstrings-python==1.18.2; extra == "docs"
Provides-Extra: types
Requires-Dist: types-python-dateutil; extra == "types"
Requires-Dist: types-PyYAML==6.0.12.20250915; extra == "types"
Requires-Dist: types-Pygments==2.19.0.20250809; extra == "types"
Requires-Dist: types-ujson==5.10.0.20250822; extra == "types"
Requires-Dist: types-requests==2.32.0.20240602; extra == "types"
Provides-Extra: app
Requires-Dist: uvicorn[standard]==0.35.0; extra == "app"
Requires-Dist: fastapi==0.116.1; extra == "app"
Provides-Extra: grout
Requires-Dist: proxy.py==2.4.10; extra == "grout"
Provides-Extra: silence
Requires-Dist: webrtcvad==2.0.10; extra == "silence"
Requires-Dist: setuptools==80.9.0; extra == "silence"
Provides-Extra: transcribe
Requires-Dist: openai-whisper==20240930; extra == "transcribe"
Requires-Dist: numpy==1.26.4; extra == "transcribe"
Provides-Extra: openai
Requires-Dist: openai==2.1.0; extra == "openai"
Provides-Extra: release
Requires-Dist: build; extra == "release"
Requires-Dist: twine; extra == "release"
Dynamic: download-url
Dynamic: license-file
